z3c.recipe.sphinxdoc-1.1.0-py3.5-nspkg.pth
z3c/recipe/sphinxdoc/__init__.py
z3c/recipe/sphinxdoc/default.css
z3c/recipe/sphinxdoc/index.rst
z3c/recipe/sphinxdoc/layout.html
z3c/recipe/sphinxdoc/tests/__init__.py
z3c/recipe/sphinxdoc/tests/test_sphinxdoc.py
z3c.recipe.sphinxdoc-1.1.0.dist-info/DESCRIPTION.rst
z3c.recipe.sphinxdoc-1.1.0.dist-info/METADATA
z3c.recipe.sphinxdoc-1.1.0.dist-info/RECORD
z3c.recipe.sphinxdoc-1.1.0.dist-info/WHEEL
z3c.recipe.sphinxdoc-1.1.0.dist-info/entry_points.txt
z3c.recipe.sphinxdoc-1.1.0.dist-info/metadata.json
z3c.recipe.sphinxdoc-1.1.0.dist-info/namespace_packages.txt
z3c.recipe.sphinxdoc-1.1.0.dist-info/top_level.txt
