Metadata-Version: 1.1
Name: z3c.recipe.sphinxdoc
Version: 1.1.0
Summary: Use Sphinx to build documentation for zope.org.
Home-page: https://github.com/zopefoundation/z3c.recipe.sphinxdoc/
Author: Paul Carduner, Zope Foundation and Contributors
Author-email: zope-dev@zope.org
License: ZPL 2.1
Keywords: buildout sphinx docs recipe
Platform: UNKNOWN
Classifier: Development Status :: 5 - Production/Stable
Classifier: Intended Audience :: Developers
Classifier: License :: OSI Approved :: Zope Public License
Classifier: Programming Language :: Python
Classifier: Programming Language :: Python :: 2
Classifier: Programming Language :: Python :: 2.7
Classifier: Programming Language :: Python :: 3
Classifier: Programming Language :: Python :: 3.4
Classifier: Programming Language :: Python :: 3.5
Classifier: Programming Language :: Python :: 3.6
Classifier: Programming Language :: Python :: Implementation :: CPython
Classifier: Programming Language :: Python :: Implementation :: PyPy
Classifier: Natural Language :: English
Classifier: Operating System :: OS Independent
Classifier: Framework :: Buildout
